[
  {
    "business_id": "FbZaWTOOaLwTI_zVbtE5OA", 
    "business_name": "Mecklenburg Medical Group", 
    "checkin_info": {
      "0-5": 1, 
      "11-3": 1, 
      "12-0": 1, 
      "12-2": 1, 
      "12-4": 1, 
      "12-5": 1, 
      "16-2": 1, 
      "4-0": 1, 
      "4-1": 1, 
      "5-1": 1, 
      "6-0": 1, 
      "6-2": 2, 
      "6-4": 1, 
      "7-2": 1, 
      "9-0": 1, 
      "9-3": 1
    }, 
    "total_checkin": 17, 
    "type": "checkin"
  }, 
  {
    "business_id": "mhotbecZYG8wonnw6yLdcQ", 
    "business_name": "Dermatology Laser & Vein Specialists of the Carolinas PLLC", 
    "checkin_info": {
      "10-0": 1, 
      "11-0": 1, 
      "12-0": 2, 
      "13-1": 1, 
      "4-1": 1, 
      "4-4": 1, 
      "5-0": 3, 
      "5-3": 2, 
      "5-4": 1, 
      "6-2": 1, 
      "6-3": 1, 
      "8-3": 1, 
      "9-2": 1
    }, 
    "total_checkin": 17, 
    "type": "checkin"
  }, 
  {
    "business_id": "gml0sUVxgcw4qk3SRK6rfg", 
    "business_name": "Charlotte Dermatology", 
    "checkin_info": {
      "10-2": 1, 
      "10-3": 1, 
      "10-4": 1, 
      "5-1": 1, 
      "6-2": 1, 
      "7-4": 1, 
      "9-0": 2
    }, 
    "total_checkin": 8, 
    "type": "checkin"
  }, 
  {
    "business_id": "xzy5-n_BQ97ImX-VtW85eA", 
    "business_name": "Darst Dermatology", 
    "checkin_info": {
      "11-0": 1, 
      "12-3": 1, 
      "12-4": 1, 
      "5-1": 1, 
      "7-1": 1, 
      "7-3": 1, 
      "8-4": 1
    }, 
    "total_checkin": 7, 
    "type": "checkin"
  }, 
  {
    "business_id": "nlydw1AyMNahxtyJdt_2bA", 
    "business_name": "South Charlotte Dermatology", 
    "checkin_info": {
      "12-2": 1, 
      "6-3": 1, 
      "7-2": 1, 
      "7-5": 1, 
      "8-3": 1
    }, 
    "total_checkin": 5, 
    "type": "checkin"
  }
]