[
  {
    "business_id": "QclAMzo7Gb5eZjT6oVvyMQ", 
    "business_name": "Dutch Mill Sports Club", 
    "checkin_info": {
      "10-4": 2, 
      "11-0": 1, 
      "11-4": 5, 
      "12-4": 8, 
      "12-6": 1, 
      "13-4": 2, 
      "14-3": 1, 
      "15-0": 1, 
      "15-2": 2, 
      "16-1": 4, 
      "16-2": 2, 
      "17-0": 1, 
      "17-1": 4, 
      "17-4": 4, 
      "17-5": 1, 
      "18-1": 1, 
      "18-4": 39, 
      "18-5": 9, 
      "19-2": 2, 
      "19-4": 6, 
      "19-5": 8, 
      "20-4": 1, 
      "20-5": 3, 
      "21-1": 1, 
      "21-5": 2, 
      "22-4": 1, 
      "22-5": 2, 
      "9-4": 2, 
      "9-5": 5
    }, 
    "total_checkin": 121, 
    "type": "checkin"
  }, 
  {
    "business_id": "5JOVLm1SYfXPCO3OUZqVtg", 
    "business_name": "Karaoke Kid", 
    "checkin_info": {
      "19-1": 1, 
      "19-5": 2, 
      "20-2": 1, 
      "20-4": 1, 
      "20-5": 3, 
      "21-1": 1, 
      "21-3": 1, 
      "21-4": 4, 
      "21-5": 4, 
      "22-2": 1, 
      "22-3": 2, 
      "22-4": 3, 
      "22-5": 2, 
      "23-1": 1, 
      "23-3": 1, 
      "23-4": 4, 
      "23-5": 1, 
      "5-0": 1
    }, 
    "total_checkin": 34, 
    "type": "checkin"
  }, 
  {
    "business_id": "k4JV4ZZpePUvyYRB56k75g", 
    "business_name": "Sol Azteca Fusion Grill", 
    "checkin_info": {
      "10-1": 1, 
      "10-3": 2, 
      "11-2": 1, 
      "11-5": 1, 
      "12-5": 1, 
      "13-4": 1, 
      "16-3": 1, 
      "16-4": 1, 
      "16-6": 1, 
      "17-1": 1, 
      "17-4": 1, 
      "18-0": 1, 
      "18-1": 1, 
      "19-0": 1, 
      "19-4": 1, 
      "19-5": 1, 
      "20-3": 1, 
      "21-3": 1, 
      "21-5": 1, 
      "8-4": 1
    }, 
    "total_checkin": 21, 
    "type": "checkin"
  }
]