[
  {
    "business_id": "eG3Kxpv-JOLib9o5W9Aiyw", 
    "business_name": "A Pig In a Fur Coat", 
    "checkin_info": {
      "10-2": 1, 
      "11-6": 1, 
      "12-3": 1, 
      "13-1": 1, 
      "13-5": 1, 
      "14-0": 3, 
      "14-1": 2, 
      "14-2": 3, 
      "14-3": 1, 
      "14-4": 3, 
      "14-5": 4, 
      "15-0": 5, 
      "15-1": 6, 
      "15-2": 3, 
      "15-3": 4, 
      "15-4": 6, 
      "15-5": 16, 
      "16-0": 9, 
      "16-1": 8, 
      "16-2": 13, 
      "16-3": 12, 
      "16-4": 14, 
      "16-5": 18, 
      "16-6": 1, 
      "17-0": 17, 
      "17-1": 19, 
      "17-2": 14, 
      "17-3": 17, 
      "17-4": 23, 
      "17-5": 26, 
      "17-6": 1, 
      "18-0": 13, 
      "18-1": 9, 
      "18-2": 7, 
      "18-3": 9, 
      "18-4": 16, 
      "18-5": 22, 
      "19-0": 4, 
      "19-1": 1, 
      "19-2": 5, 
      "19-3": 6, 
      "19-4": 11, 
      "19-5": 5, 
      "20-0": 1, 
      "20-2": 1, 
      "20-3": 2, 
      "20-5": 2, 
      "21-3": 1, 
      "21-4": 1, 
      "22-6": 1, 
      "7-1": 1, 
      "7-6": 1, 
      "9-1": 1, 
      "9-2": 1
    }, 
    "total_checkin": 374, 
    "type": "checkin"
  }, 
  {
    "business_id": "vogZZuDmuVZmKssoZ11Kyw", 
    "business_name": "Banzo", 
    "checkin_info": {
      "10-0": 2, 
      "10-1": 11, 
      "10-2": 11, 
      "10-3": 9, 
      "10-4": 16, 
      "10-5": 11, 
      "11-0": 4, 
      "11-1": 8, 
      "11-2": 7, 
      "11-3": 6, 
      "11-4": 8, 
      "11-5": 9, 
      "12-0": 4, 
      "12-1": 1, 
      "12-2": 5, 
      "12-4": 5, 
      "12-5": 4, 
      "12-6": 1, 
      "13-1": 2, 
      "13-3": 4, 
      "13-4": 3, 
      "13-5": 2, 
      "14-1": 2, 
      "14-2": 2, 
      "14-4": 1, 
      "14-5": 5, 
      "14-6": 1, 
      "15-0": 4, 
      "15-1": 1, 
      "15-2": 2, 
      "15-3": 3, 
      "15-4": 4, 
      "15-5": 4, 
      "16-1": 8, 
      "16-2": 5, 
      "16-3": 3, 
      "16-4": 5, 
      "16-5": 4, 
      "17-0": 8, 
      "17-1": 2, 
      "17-2": 4, 
      "17-3": 6, 
      "17-4": 10, 
      "17-5": 6, 
      "18-0": 2, 
      "18-1": 6, 
      "18-2": 3, 
      "18-3": 2, 
      "18-4": 3, 
      "18-5": 3, 
      "19-0": 1, 
      "19-1": 1, 
      "19-4": 1, 
      "21-4": 1, 
      "22-4": 2, 
      "8-5": 1, 
      "9-0": 4, 
      "9-1": 5, 
      "9-2": 4, 
      "9-3": 7, 
      "9-4": 4, 
      "9-5": 1
    }, 
    "total_checkin": 274, 
    "type": "checkin"
  }, 
  {
    "business_id": "8GlGakyGqp9WvToKcnJmxg", 
    "business_name": "Nostrano", 
    "checkin_info": {
      "10-1": 1, 
      "10-3": 6, 
      "10-4": 5, 
      "11-0": 2, 
      "11-1": 2, 
      "11-3": 1, 
      "11-4": 2, 
      "14-4": 1, 
      "14-5": 1, 
      "15-0": 2, 
      "15-1": 1, 
      "15-2": 2, 
      "15-3": 3, 
      "15-4": 6, 
      "15-5": 5, 
      "16-0": 3, 
      "16-1": 6, 
      "16-2": 4, 
      "16-3": 5, 
      "16-4": 4, 
      "16-5": 12, 
      "17-0": 7, 
      "17-1": 12, 
      "17-2": 7, 
      "17-3": 5, 
      "17-4": 6, 
      "17-5": 8, 
      "18-0": 3, 
      "18-1": 9, 
      "18-2": 3, 
      "18-3": 2, 
      "18-4": 10, 
      "18-5": 9, 
      "19-0": 1, 
      "19-2": 2, 
      "19-3": 8, 
      "19-4": 7, 
      "19-5": 7, 
      "20-4": 2, 
      "20-5": 3, 
      "21-1": 1, 
      "21-2": 1, 
      "21-4": 1, 
      "21-5": 2, 
      "7-4": 1, 
      "8-5": 1, 
      "9-1": 2, 
      "9-6": 1
    }, 
    "total_checkin": 195, 
    "type": "checkin"
  }, 
  {
    "business_id": "ed5VpqG6NlI2_ALQpZ0lLA", 
    "business_name": "Mediterranean Cafe", 
    "checkin_info": {
      "10-0": 2, 
      "10-1": 10, 
      "10-2": 12, 
      "10-3": 5, 
      "10-4": 11, 
      "10-5": 3, 
      "11-0": 5, 
      "11-1": 13, 
      "11-2": 7, 
      "11-3": 6, 
      "11-4": 12, 
      "11-5": 4, 
      "12-0": 2, 
      "12-1": 2, 
      "12-2": 6, 
      "12-3": 2, 
      "12-4": 3, 
      "12-5": 4, 
      "13-0": 3, 
      "13-1": 4, 
      "13-2": 3, 
      "13-3": 4, 
      "13-4": 2, 
      "13-5": 3, 
      "14-1": 1, 
      "14-2": 2, 
      "14-3": 1, 
      "14-4": 1, 
      "14-5": 2, 
      "15-0": 1, 
      "15-2": 2, 
      "15-3": 1, 
      "15-4": 1, 
      "16-3": 1, 
      "16-4": 2, 
      "16-5": 1, 
      "19-5": 1, 
      "2-2": 1, 
      "20-1": 1, 
      "21-2": 2, 
      "21-6": 1, 
      "22-0": 1, 
      "22-3": 1, 
      "22-6": 1, 
      "23-1": 1, 
      "3-0": 1, 
      "3-2": 1, 
      "3-5": 2, 
      "5-0": 1, 
      "7-4": 1, 
      "7-5": 1, 
      "8-1": 2, 
      "8-2": 2, 
      "8-3": 1, 
      "8-4": 1, 
      "8-5": 3, 
      "9-0": 5, 
      "9-1": 4, 
      "9-2": 2, 
      "9-3": 6, 
      "9-4": 4, 
      "9-5": 3
    }, 
    "total_checkin": 194, 
    "type": "checkin"
  }, 
  {
    "business_id": "cFZj6p-KEiAZokMPbjuMRA", 
    "business_name": "Novanta", 
    "checkin_info": {
      "10-0": 3, 
      "10-1": 4, 
      "10-2": 2, 
      "10-3": 5, 
      "10-4": 3, 
      "10-5": 1, 
      "10-6": 5, 
      "11-0": 1, 
      "11-1": 2, 
      "11-2": 1, 
      "11-3": 4, 
      "11-4": 6, 
      "11-5": 2, 
      "11-6": 2, 
      "12-0": 1, 
      "12-2": 1, 
      "12-5": 2, 
      "12-6": 2, 
      "13-2": 2, 
      "13-6": 3, 
      "14-1": 1, 
      "14-4": 1, 
      "14-5": 1, 
      "14-6": 1, 
      "15-0": 1, 
      "15-2": 2, 
      "15-3": 3, 
      "15-4": 6, 
      "15-5": 4, 
      "15-6": 4, 
      "16-0": 4, 
      "16-1": 3, 
      "16-2": 1, 
      "16-3": 9, 
      "16-4": 4, 
      "16-5": 7, 
      "16-6": 7, 
      "17-0": 2, 
      "17-1": 2, 
      "17-2": 1, 
      "17-3": 3, 
      "17-4": 4, 
      "17-5": 7, 
      "17-6": 2, 
      "18-0": 1, 
      "18-1": 2, 
      "18-2": 2, 
      "18-3": 1, 
      "18-4": 1, 
      "18-5": 2, 
      "19-1": 2, 
      "19-2": 1, 
      "19-3": 1, 
      "21-5": 1, 
      "22-5": 1, 
      "9-0": 1, 
      "9-2": 1, 
      "9-3": 3, 
      "9-5": 2
    }, 
    "total_checkin": 154, 
    "type": "checkin"
  }, 
  {
    "business_id": "dOo_jUaYeHC4b6bgOytinw", 
    "business_name": "Otto's Restaurant & Bar", 
    "checkin_info": {
      "0-0": 1, 
      "1-5": 1, 
      "10-1": 1, 
      "10-5": 1, 
      "11-0": 1, 
      "11-1": 3, 
      "11-5": 1, 
      "11-6": 1, 
      "12-4": 1, 
      "12-6": 1, 
      "13-1": 1, 
      "13-4": 3, 
      "13-6": 1, 
      "14-0": 2, 
      "14-1": 2, 
      "14-2": 1, 
      "14-4": 4, 
      "14-5": 3, 
      "15-1": 1, 
      "15-2": 1, 
      "15-3": 2, 
      "15-4": 5, 
      "15-5": 5, 
      "15-6": 1, 
      "16-1": 8, 
      "16-2": 4, 
      "16-3": 3, 
      "16-4": 8, 
      "16-5": 6, 
      "17-1": 2, 
      "17-2": 2, 
      "17-3": 4, 
      "17-4": 6, 
      "17-5": 8, 
      "17-6": 1, 
      "18-1": 7, 
      "18-2": 6, 
      "18-3": 3, 
      "18-4": 3, 
      "18-5": 4, 
      "19-0": 1, 
      "19-2": 1, 
      "19-4": 3, 
      "19-5": 3, 
      "19-6": 1, 
      "20-0": 1, 
      "20-1": 1, 
      "20-4": 2, 
      "20-5": 1, 
      "22-5": 1, 
      "23-5": 1, 
      "5-0": 1, 
      "5-5": 1, 
      "8-3": 4, 
      "8-5": 2
    }, 
    "total_checkin": 143, 
    "type": "checkin"
  }, 
  {
    "business_id": "OXLegbUo6HA3DN3lBFTsUg", 
    "business_name": "Parthenon Gyros Restaurant", 
    "checkin_info": {
      "0-2": 1, 
      "0-5": 2, 
      "0-6": 3, 
      "1-2": 1, 
      "10-0": 1, 
      "10-1": 2, 
      "10-2": 3, 
      "10-3": 2, 
      "10-4": 2, 
      "10-5": 5, 
      "10-6": 1, 
      "11-0": 1, 
      "11-1": 4, 
      "11-2": 1, 
      "11-3": 1, 
      "11-4": 2, 
      "11-5": 5, 
      "11-6": 2, 
      "12-4": 4, 
      "12-5": 2, 
      "12-6": 6, 
      "13-2": 1, 
      "13-3": 1, 
      "13-5": 1, 
      "14-2": 1, 
      "14-4": 1, 
      "14-5": 2, 
      "14-6": 3, 
      "15-0": 1, 
      "15-2": 2, 
      "15-4": 3, 
      "15-5": 2, 
      "16-0": 2, 
      "16-2": 2, 
      "16-3": 2, 
      "16-4": 1, 
      "16-5": 3, 
      "16-6": 2, 
      "17-1": 1, 
      "17-3": 4, 
      "17-4": 1, 
      "17-6": 2, 
      "18-1": 2, 
      "18-2": 1, 
      "18-3": 4, 
      "19-2": 1, 
      "19-3": 1, 
      "19-4": 4, 
      "19-6": 2, 
      "20-1": 1, 
      "20-3": 2, 
      "20-4": 1, 
      "20-5": 3, 
      "21-0": 1, 
      "21-1": 2, 
      "21-4": 1, 
      "21-5": 3, 
      "21-6": 1, 
      "22-1": 1, 
      "22-4": 1, 
      "22-5": 1, 
      "22-6": 2, 
      "23-0": 1, 
      "23-1": 1, 
      "23-2": 1, 
      "23-6": 2, 
      "7-2": 1, 
      "9-1": 2, 
      "9-2": 1, 
      "9-4": 1, 
      "9-5": 1, 
      "9-6": 1
    }, 
    "total_checkin": 136, 
    "type": "checkin"
  }, 
  {
    "business_id": "0pXk2JkijBpi2Iz0D5pFXA", 
    "business_name": "Kabul Restaurant", 
    "checkin_info": {
      "10-0": 3, 
      "10-1": 2, 
      "10-2": 1, 
      "10-4": 4, 
      "10-5": 1, 
      "10-6": 3, 
      "11-0": 1, 
      "11-1": 2, 
      "11-2": 3, 
      "11-3": 1, 
      "11-4": 1, 
      "11-5": 3, 
      "11-6": 3, 
      "12-0": 1, 
      "12-1": 1, 
      "12-4": 1, 
      "12-5": 2, 
      "12-6": 3, 
      "13-4": 1, 
      "13-5": 3, 
      "14-0": 1, 
      "14-1": 3, 
      "14-4": 3, 
      "14-5": 1, 
      "14-6": 3, 
      "15-0": 1, 
      "15-4": 1, 
      "15-5": 2, 
      "15-6": 1, 
      "16-0": 1, 
      "16-1": 3, 
      "16-2": 4, 
      "16-3": 1, 
      "16-4": 1, 
      "16-5": 8, 
      "16-6": 2, 
      "17-1": 2, 
      "17-2": 3, 
      "17-3": 4, 
      "17-4": 4, 
      "17-5": 3, 
      "17-6": 2, 
      "18-2": 1, 
      "18-3": 1, 
      "18-5": 5, 
      "18-6": 1, 
      "19-0": 1, 
      "19-1": 1, 
      "19-4": 1, 
      "19-5": 2, 
      "19-6": 2, 
      "20-1": 1, 
      "20-4": 2, 
      "21-0": 1, 
      "22-4": 1, 
      "5-3": 1, 
      "6-2": 1, 
      "6-5": 1, 
      "8-4": 1, 
      "9-1": 3, 
      "9-4": 1, 
      "9-5": 1, 
      "9-6": 3
    }, 
    "total_checkin": 126, 
    "type": "checkin"
  }, 
  {
    "business_id": "M1n4HVSdD9FIyfmIoxxRrg", 
    "business_name": "Bunky's Cafe", 
    "checkin_info": {
      "10-1": 1, 
      "10-2": 1, 
      "10-3": 1, 
      "10-4": 3, 
      "10-5": 4, 
      "11-1": 1, 
      "11-2": 1, 
      "11-3": 1, 
      "11-4": 4, 
      "12-5": 2, 
      "12-6": 1, 
      "13-5": 1, 
      "14-2": 1, 
      "14-4": 2, 
      "14-5": 2, 
      "15-4": 1, 
      "15-5": 2, 
      "15-6": 2, 
      "16-0": 1, 
      "16-1": 2, 
      "16-2": 1, 
      "16-3": 3, 
      "16-4": 5, 
      "16-5": 2, 
      "16-6": 3, 
      "17-0": 2, 
      "17-1": 1, 
      "17-2": 4, 
      "17-3": 3, 
      "17-4": 6, 
      "17-5": 6, 
      "17-6": 2, 
      "18-3": 3, 
      "18-4": 3, 
      "18-5": 4, 
      "18-6": 2, 
      "19-0": 1, 
      "19-3": 1, 
      "19-4": 4, 
      "19-5": 1, 
      "20-5": 1, 
      "7-2": 1, 
      "8-4": 1, 
      "9-3": 1, 
      "9-4": 2, 
      "9-5": 1
    }, 
    "total_checkin": 98, 
    "type": "checkin"
  }, 
  {
    "business_id": "3KUwS1FedV0_L5y_D9YAiQ", 
    "business_name": "Palmyra Mediterranean Grill", 
    "checkin_info": {
      "10-0": 2, 
      "10-1": 1, 
      "10-3": 4, 
      "10-4": 2, 
      "10-6": 4, 
      "11-1": 1, 
      "11-2": 1, 
      "11-3": 3, 
      "11-4": 1, 
      "11-5": 2, 
      "11-6": 2, 
      "12-0": 2, 
      "12-1": 1, 
      "12-5": 1, 
      "12-6": 2, 
      "13-4": 2, 
      "13-5": 1, 
      "13-6": 2, 
      "14-0": 1, 
      "14-3": 1, 
      "14-5": 2, 
      "15-0": 1, 
      "15-1": 1, 
      "15-3": 1, 
      "15-4": 1, 
      "15-6": 1, 
      "16-0": 3, 
      "16-1": 2, 
      "16-2": 3, 
      "16-3": 1, 
      "16-5": 1, 
      "16-6": 2, 
      "17-0": 1, 
      "17-1": 1, 
      "17-2": 3, 
      "17-3": 2, 
      "17-4": 6, 
      "17-5": 1, 
      "17-6": 1, 
      "18-0": 2, 
      "18-3": 3, 
      "18-4": 1, 
      "18-5": 1, 
      "19-1": 2, 
      "19-2": 1, 
      "19-5": 2, 
      "20-5": 1, 
      "21-2": 2, 
      "22-3": 1, 
      "23-1": 1, 
      "23-3": 1, 
      "9-5": 1, 
      "9-6": 1
    }, 
    "total_checkin": 90, 
    "type": "checkin"
  }
]